globsync/__init__.py
globsync/__main__.py
globsync/cli.py
globsync/utils/__init__.py
globsync/utils/config.py
globsync/utils/db.py
globsync/utils/logging.py
globsync/utils/paths.py
globsync/utils/status.py
globsync/utils/users.py
globsync/utils/email/__init__.py
globsync/utils/email/gmail.py
globsync/utils/email/linux_mail.py
globsync/utils/email/office365.py
globsync/utils/email/smtp.py
globsync/utils/email/templates/user_notification.html
globsync/utils/flows/__init__.py
globsync/utils/flows/action_providers/transfer/transfer_input_schema.json
globsync/utils/flows/definitions/transfer.json
globsync/utils/flows/input-schemas/transfer.json
globsync-0.1.0.dist-info/licenses/LICENSE
globsync-0.1.0.dist-info/METADATA
globsync-0.1.0.dist-info/WHEEL
globsync-0.1.0.dist-info/entry_points.txt
globsync-0.1.0.dist-info/top_level.txt
globsync-0.1.0.dist-info/RECORD
