Metadata-Version: 2.4
Name: globsync
Version: 0.1.0
Summary: An automatic backup monitoring tool using Globus as backend
Author-email: Samuel Corveleyn <samuel.corveleyn@kuleuven.be>
Project-URL: Homepage, https://gitlab.kuleuven.be/ees/rdm/globsync.git
Project-URL: Issues, https://gitlab.kuleuven.be/ees/rdm/globsync/-/issues
Requires-Python: >=3.8
License-File: LICENSE
Requires-Dist: PyYAML>=6.0.2
Requires-Dist: SQLAlchemy>=2.0.36
Requires-Dist: python-json-logger>=2.0.7
Requires-Dist: globus-sdk>=3.46.0
Requires-Dist: google-auth>=2.39.0
Requires-Dist: google-auth-oauthlib>=1.2.2
Requires-Dist: google-auth-httplib2>=0.2.0
Requires-Dist: google-api-python-client>=2.169.0
Requires-Dist: beautifulsoup4>=4.12.3
Requires-Dist: pandas>=2.2.2
Requires-Dist: numpy>=1.26.4
Requires-Dist: rich>=13.7.1
Requires-Dist: Jinja2>=3.1.4
Dynamic: license-file
